[
    {
        "id": "af8eccb8-fc3c-11ed-8742-0242ac160004",
        "annotations": [],
        "sr": 44100,
        "bit_depth": 2,
        "channels": [
            "Channel-1",
            "Channel-2"
        ],
        "device_id": "02:42:ac:16:00:04",
        "tt": 1685202309241392,
        "bt": 1685157309238641
    },
    {
        "id": "ecdba6b8-fd0e-11ed-a258-0242ac130004",
        "annotations": [
            {
                "name": "”iepe_radio_t10000 --timer=10\noedge-cli start-capture --annotations=”iepe_radio_t17000",
                "bt": 1685247606354985,
                "tt": 1685264606356678,
                "source": "user"
            }
        ],
        "sr": 44100,
        "bit_depth": 2,
        "channels": [
            "Channel-1",
            "Channel-2"
        ],
        "device_id": "02:42:ac:13:00:04",
        "tt": 1685264606356678,
        "bt": 1685247606354985
    },
    {
        "id": "fe98d29a-fd0e-11ed-a2ce-0242ac130004",
        "annotations": [
            {
                "name": "sys76_ac13_sineWave_t24000",
                "bt": 1685247636116361,
                "tt": 1685271636118322,
                "source": "user"
            }
        ],
        "sr": 44100,
        "bit_depth": 2,
        "channels": [
            "Channel-1"
        ],
        "device_id": "02:42:ac:13:00:04",
        "tt": 1685271636118322,
        "bt": 1685247636116361
    }
]